LICENSE.txt
MANIFEST.in
README.rst
setup.py
phenotype_cover.egg-info/PKG-INFO
phenotype_cover.egg-info/SOURCES.txt
phenotype_cover.egg-info/dependency_links.txt
phenotype_cover.egg-info/requires.txt
phenotype_cover.egg-info/top_level.txt
src/phenotype_cover/__init__.py
src/phenotype_cover/_base.py
src/phenotype_cover/_gci_wrapper.py
src/phenotype_cover/_logger.py
src/phenotype_cover/_operations.py
src/phenotype_cover/_phenotype_cover.py
tests/test_pairmat_construction.py
tests/test_phenotype_cover.py